{
  "posts": [
    {
      "slug": "1-weekly-standup",
      "date": "April 16, 2025",
      "title": "#1 The Weekly Standup",
      "draft": false,
      "description": "AI agents, Go tooling, salary negotiation tips, writing hacks, and quirky discoveries.",
      "keywords": [
        "programming",
        "saas",
        "weekly stand‑up newsletter",
        "software engineering",
        "artificial intelligence",
        "Go"
      ],
      "author": "Patrick Prunty",
      "authorUrl": "https://patrickprunty.com/about",
      "image": "/images/1-weekly-standup/cows.webp",
      "readingTime": 7
    },
    {
      "slug": "2-weekly-standup",
      "date": "April 21, 2025",
      "title": "#2 The Weekly Standup",
      "draft": true,
      "description": "to be filled",
      "keywords": [
        "newsletter",
        "AI",
        "software development"
      ],
      "author": "Patrick Prunty",
      "authorUrl": "https://patrickprunty.com/about",
      "image": "/images/2-weekly-standup/2-weekly-standup.webp",
      "readingTime": 1
    },
    {
      "slug": "indie-hackers-and-liars",
      "date": "April 6, 2025",
      "title": "Indie Hackers and Liars",
      "draft": true,
      "description": "to be filled",
      "keywords": [
        "indiehacker",
        "liars",
        "buildinpublic",
        "bootstrapping",
        "programming",
        "saas",
        "startup",
        "FOMO"
      ],
      "author": "Patrick Prunty",
      "authorUrl": "https://patrickprunty.com/about",
      "image": "/images/indie-hackers-and-liars/indie-hackers-and-liars3.webp",
      "readingTime": 1
    },
    {
      "slug": "the-engineers-proclivity-for-perfection",
      "date": "March 18, 2025",
      "title": "The Engineer's Proclivity for Perfection",
      "draft": false,
      "description": "Or: Why It'll Never Be Perfect—Let Alone \"Done\".",
      "keywords": [
        "software development",
        "engineering",
        "programming",
        "perfection",
        "productivity",
        "technology"
      ],
      "author": "Patrick Prunty",
      "authorUrl": "https://patrickprunty.com/about",
      "image": "/images/the-engineers-proclivity-for-perfection/gg_resized.webp",
      "readingTime": 2
    },
    {
      "slug": "the-winds-of-winter-preview-chapters-free-ebook-kindle-and-pdf-download",
      "date": "December 10, 2024",
      "title": "The Winds of Winter Preview Chapters: Free eBook, Kindle, and PDF Download",
      "draft": false,
      "description": "Download preview chapters of The Winds of Winter by George R.R. Martin in eBook, Kindle, or PDF formats.",
      "keywords": [
        "fantasy",
        "ASOIAF",
        "Game of Thrones",
        "ebook",
        "pdf",
        "George R.R. Martin",
        "reading",
        "book preview",
        "downloads"
      ],
      "author": "Patrick Prunty",
      "authorUrl": "https://patrickprunty.com/about",
      "image": "/images/the-winds-of-winter-preview-chapters-free-ebook-kindle-and-pdf-download/twow.webp",
      "readingTime": 2
    },
    {
      "slug": "untitled-01",
      "date": "July 18, 2024",
      "title": "Untitled 01",
      "draft": false,
      "description": "An experimental poem by Patrick Prunty.",
      "keywords": [
        "poetry",
        "experimental writing",
        "creative writing",
        "writing"
      ],
      "author": "Patrick Prunty",
      "authorUrl": "https://patrickprunty.com",
      "image": "/images/untitled-01/splash.webp",
      "readingTime": 2
    },
    {
      "slug": "what-is-blogging",
      "date": "February 3, 2025",
      "title": "What is Blogging?",
      "draft": true,
      "description": "Or why in a world full of people trying to be somebody else, you should focus on being you.",
      "keywords": [
        "blogging",
        "authenticity",
        "content creation",
        "self-expression",
        "writing"
      ],
      "author": "Patrick Prunty",
      "authorUrl": "https://patrickprunty.com/about",
      "image": "/images/what-is-blogging/what-is-blogging.webp",
      "readingTime": 4
    },
    {
      "slug": "why-im-optimistic-ai-wont-take-my-swe-job",
      "date": "February 10, 2025",
      "title": "Why I’m Optimistic AI Won’t Take My SWE Job",
      "draft": true,
      "description": "Or why AI is but another abstraction layer for software development. ",
      "keywords": [
        "AI",
        "software engineering",
        "programming",
        "technology",
        "job security"
      ],
      "author": "Patrick Prunty",
      "authorUrl": "https://patrickprunty.com/about",
      "image": "/images/why-im-optimistic-ai-wont-take-my-swe-job/why-im-optimistic-ai-wont-take-my-swe-job.webp",
      "readingTime": 2
    }
  ]
}